scrubadubdub/__init__.py
scrubadubdub/cli.py
scrubadubdub/scrub.py
scrubadubdub-0.2.1.dist-info/LICENSE
scrubadubdub-0.2.1.dist-info/METADATA
scrubadubdub-0.2.1.dist-info/WHEEL
scrubadubdub-0.2.1.dist-info/entry_points.txt
scrubadubdub-0.2.1.dist-info/RECORD
