Metadata-Version: 2.1
Name: scrubadubdub
Version: 0.2.1
Summary: A Python package to scrub PII
Home-page: https://github.com/kylemclaren/scrub
License: MIT
Author: Kyle McLaren
Author-email: kylemclaren@protonmail.com
Requires-Python: >=3.9,<3.11
Classifier: License :: OSI Approved :: MIT License
Classifier: Programming Language :: Python :: 3
Classifier: Programming Language :: Python :: 3.9
Classifier: Programming Language :: Python :: 3.10
Requires-Dist: halo (>=0.0.31,<0.0.32)
Requires-Dist: ipaddress (>=1.0.23,<2.0.0)
Requires-Dist: numpy (>=1.24.2,<2.0.0)
Requires-Dist: phonenumbers (>=8.13.8,<9.0.0)
Requires-Dist: spacy (>=3.5.1,<4.0.0)
Project-URL: Repository, https://github.com/kylemclaren/scrub
